gpt_batch/__init__.py
gpt_batch/batcher.py
tests/__init__.py
tests/test_batcher.py
gpt_batch-0.1.9.dist-info/METADATA
gpt_batch-0.1.9.dist-info/WHEEL
gpt_batch-0.1.9.dist-info/top_level.txt
gpt_batch-0.1.9.dist-info/RECORD
