Metadata-Version: 2.1
Name: gpt-batch
Version: 0.1.9
Summary: A package for batch processing with OpenAI API.
Home-page: https://github.com/fengsxy/gpt_batch
Author: Ted Yu
Author-email: liddlerain@gmail.com
License: UNKNOWN
Platform: UNKNOWN
Requires-Dist: openai
Requires-Dist: tqdm
Requires-Dist: anthropic
